quant_vnpy/__init__.py
quant_vnpy/config.py
quant_vnpy/constants.py
quant_vnpy/logging.py
quant_vnpy/backtest/__init__.py
quant_vnpy/backtest/commons.py
quant_vnpy/backtest/cta_strategy/__init__.py
quant_vnpy/backtest/cta_strategy/engine.py
quant_vnpy/backtest/cta_strategy/run.py
quant_vnpy/backtest/cta_strategy/template.py
quant_vnpy/backtest/maintain/__init__.py
quant_vnpy/backtest/maintain/strategy_stats.py
quant_vnpy/backtest/maintain/track_performance.py
quant_vnpy/backtest/portfolio_strategy/__init__.py
quant_vnpy/backtest/portfolio_strategy/engine.py
quant_vnpy/backtest/portfolio_strategy/run.py
quant_vnpy/backtest/portfolio_strategy/template.py
quant_vnpy/db/__init__.py
quant_vnpy/db/backtest_strategy_stats.py
quant_vnpy/db/orm.py
quant_vnpy/db/utils.py
quant_vnpy/report/__init__.py
quant_vnpy/report/collector.py
quant_vnpy/report/data_available_check.py
quant_vnpy/report/monitor.py
quant_vnpy/utils/__init__.py
quant_vnpy/utils/cta_signal.py
quant_vnpy/utils/data.py
quant_vnpy/utils/enhancement.py
quant_vnpy/utils/param_opt_result.py
quant_vnpy-0.6.0.dist-info/METADATA
quant_vnpy-0.6.0.dist-info/WHEEL
quant_vnpy-0.6.0.dist-info/top_level.txt
quant_vnpy-0.6.0.dist-info/RECORD
