Metadata-Version: 2.1
Name: quant-vnpy
Version: 0.6.0
Summary: 基于VNPY进行功能增强
Home-page: http://192.168.0.103/quant/quant_vnpy
Author: MG
Author-email: mmmaaaggg@163.com
License: UNKNOWN
Platform: UNKNOWN
Classifier: Programming Language :: Python :: 3 :: Only
Classifier: Programming Language :: Python :: 3.7
Classifier: Operating System :: Microsoft :: Windows
Classifier: Operating System :: Unix
Classifier: Operating System :: POSIX
Classifier: License :: OSI Approved :: MIT License
Classifier: Development Status :: 5 - Production/Stable
Classifier: Environment :: No Input/Output (Daemon)
Classifier: Intended Audience :: Developers
Classifier: Natural Language :: Chinese (Simplified)
Classifier: Topic :: Software Development
Requires-Python: >=3.6
Requires-Dist: IBATS-Common (>=0.20.8)
Requires-Dist: psutil (>=5.7.2)
Requires-Dist: kaleido (>=0.0.3)
Requires-Dist: openpyxl (>=3.0.5)
Requires-Dist: xlwt (>=1.3.0)
Requires-Dist: tqdm (>=4.51.0)
Requires-Dist: peewee (>=3.13.3)
Requires-Dist: mysql-connector-python (>=8.0.22)
